odoo10_addon_account_fiscal_position_rule_purchase-10.0.1.0.0.99.dev9-nspkg.pth
odoo/addons/account_fiscal_position_rule_purchase/README.rst
odoo/addons/account_fiscal_position_rule_purchase/__init__.py
odoo/addons/account_fiscal_position_rule_purchase/__manifest__.py
odoo/addons/account_fiscal_position_rule_purchase/i18n/account_fiscal_position_rule_purchase.pot
odoo/addons/account_fiscal_position_rule_purchase/i18n/es.po
odoo/addons/account_fiscal_position_rule_purchase/i18n/pt_BR.po
odoo/addons/account_fiscal_position_rule_purchase/i18n/sl.po
odoo/addons/account_fiscal_position_rule_purchase/models/__init__.py
odoo/addons/account_fiscal_position_rule_purchase/models/purchase.py
odoo/addons/account_fiscal_position_rule_purchase/security/ir.model.access.csv
odoo/addons/account_fiscal_position_rule_purchase/static/description/icon.png
odoo/addons/account_fiscal_position_rule_purchase/test/account_fiscal_position_rule_purchase.yml
odoo/addons/account_fiscal_position_rule_purchase/tests/__init__.py
odoo/addons/account_fiscal_position_rule_purchase/tests/test_account_fiscal_position_rule_purchase.py
odoo10_addon_account_fiscal_position_rule_purchase-10.0.1.0.0.99.dev9.dist-info/METADATA
odoo10_addon_account_fiscal_position_rule_purchase-10.0.1.0.0.99.dev9.dist-info/WHEEL
odoo10_addon_account_fiscal_position_rule_purchase-10.0.1.0.0.99.dev9.dist-info/namespace_packages.txt
odoo10_addon_account_fiscal_position_rule_purchase-10.0.1.0.0.99.dev9.dist-info/top_level.txt
odoo10_addon_account_fiscal_position_rule_purchase-10.0.1.0.0.99.dev9.dist-info/RECORD
